{"version": "4.1", "settings": "a1591172a35f33a1cd7acbd20b51f16b", "files": {"app_Units_py": {"hash": "7e26d58c04a263f9403baa9ebb2ad4c1", "index": {"relative_filename": "app/Units.py", "html_filename": "app_Units_py.html", "nums": [1, 87, 0, 56, 0, 0, 0]}}, "app_BattleField_py": {"hash": "97b67c0a287380a94951bd85984a13ef", "index": {"relative_filename": "app/BattleField.py", "html_filename": "app_BattleField_py.html", "nums": [1, 35, 0, 26, 0, 0, 0]}}, "app_script_py": {"hash": "0b4d535c0e652e73bf52c6fbbea13216", "index": {"relative_filename": "app/script.py", "html_filename": "app_script_py.html", "nums": [1, 37, 0, 30, 0, 0, 0]}}, "app_AttackStrategy_py": {"hash": "36f3e3b490baa5ca913b9f654c76d107", "index": {"relative_filename": "app/AttackStrategy.py", "html_filename": "app_AttackStrategy_py.html", "nums": [1, 33, 0, 22, 0, 0, 0]}}, "app_Squad_py": {"hash": "1ec0bb5aac00a74e2a51b122903e7213", "index": {"relative_filename": "app/Squad.py", "html_filename": "app_Squad_py.html", "nums": [1, 20, 0, 10, 0, 0, 0]}}, "app_Army_py": {"hash": "e91ce597f1ecc493efae7a5f0b09232e", "index": {"relative_filename": "app/Army.py", "html_filename": "app_Army_py.html", "nums": [1, 28, 0, 16, 0, 0, 0]}}, "app___init___py": {"hash": "182b2dca469bf063cbcf996d517b03da", "index": {"relative_filename": "app/__init__.py", "html_filename": "app___init___py.html", "nums": [1, 0, 0, 0, 0, 0, 0]}}}, "format": 1}